scrapy_user_agents/__init__.py
scrapy_user_agents/middlewares.py
scrapy_user_agents/user_agent_picker.py
scrapy_user_agents-0.1.0.dist-info/DESCRIPTION.rst
scrapy_user_agents-0.1.0.dist-info/METADATA
scrapy_user_agents-0.1.0.dist-info/RECORD
scrapy_user_agents-0.1.0.dist-info/WHEEL
scrapy_user_agents-0.1.0.dist-info/metadata.json
scrapy_user_agents-0.1.0.dist-info/top_level.txt
