Metadata-Version: 2.0
Name: scrapy-user-agents
Version: 0.1.0
Summary: Automatically pick an User-Agent for every request
Home-page: https://github.com/hyan15/crawler-demo/tree/master/crawling-basic/scrapy_user_agents
Author: Neal Wong
Author-email: ibprnd@gmail.com
License: New BSD License
Keywords: scrapy proxy user-agent web-scraping
Platform: UNKNOWN
Classifier: Development Status :: 5 - Production/Stable
Classifier: Framework :: Scrapy
Classifier: Intended Audience :: Developers
Classifier: License :: OSI Approved :: BSD License
Classifier: Programming Language :: Python
Classifier: Topic :: Internet :: WWW/HTTP
Requires-Dist: user-agents
